promesque/__init__.py
promesque/cli.py
promesque/lib/__init__.py
promesque/lib/exporter.py
promesque/lib/exporter_logger.py
promesque-0.0.3.dist-info/METADATA
promesque-0.0.3.dist-info/RECORD
promesque-0.0.3.dist-info/WHEEL
promesque-0.0.3.dist-info/entry_points.txt
promesque-0.0.3.dist-info/top_level.txt
