Metadata-Version: 2.1
Name: promesque
Version: 0.0.3
Summary: Configurable Prometheus exporter for results of Elasticsearch queries
Home-page: https://github.com/croesnick/promesque
Author: Carsten Rösnick-Neugebauer
Author-email: croesnick@gmail.com
License: MIT
Download-URL: https://github.com/croesnick/promesque/archive/v0.0.3.tar.gz
Keywords: prometheus,prometheus-exporter,elasticsearch
Platform: UNKNOWN
Classifier: Development Status :: 3 - Alpha
Classifier: Environment :: Console
Classifier: Intended Audience :: Developers
Classifier: Intended Audience :: System Administrators
Classifier: License :: OSI Approved :: MIT License
Classifier: Programming Language :: Python :: 3
Classifier: Programming Language :: Python :: 3.5
Classifier: Programming Language :: Python :: 3.6
Classifier: Topic :: System :: Monitoring
Classifier: Topic :: Utilities
Requires-Python: >=3.5
Requires-Dist: PyYAML (~=3.12)
Requires-Dist: click (~=6.7)
Requires-Dist: ruamel.yaml (~=0.15)
Requires-Dist: prometheus-client (~=0.2)
Requires-Dist: requests (~=2.19)
Requires-Dist: jsonpath-ng (~=1.4)
